inbq-0.10.0.dist-info/METADATA
inbq-0.10.0.dist-info/WHEEL
inbq-0.10.0.dist-info/licenses/LICENSE
inbq.libs/libgcc_s-39080030.so.1
inbq/__init__.py
inbq/_inbq.pyi
inbq/_inbq.pypy311-pp73-aarch64-linux-gnu.so
inbq/ast_nodes.py
inbq/lineage.py
inbq/py.typed
inbq-0.10.0.dist-info/RECORD
