Metadata-Version: 2.4
Name: inbq
Version: 0.10.0
Classifier: Programming Language :: Rust
Classifier: Programming Language :: Python :: 3 :: Only
Classifier: Programming Language :: Python :: 3.10
Classifier: Programming Language :: Python :: 3.11
Classifier: Programming Language :: Python :: 3.12
Classifier: Programming Language :: Python :: 3.13
License-File: LICENSE
Summary: A library for parsing BigQuery queries and extracting schema-aware, column-level lineage.
Keywords: bigquery,sql,parser,data-lineage
Author-email: Lorenzo Pratissoli <pratissolil@gmail.com>
License-Expression: MIT
Requires-Python: >=3.10
